{
  "profile": {"wealth_bracket": "ultra-HNW", "situation_class": "entrepreneur",
              "location": "New York, NY", "risk_tolerance": "aggressive"},
  "income_sources": [
    {"source_name": "business_distribution", "amount_per_period": 120000, "frequency": "monthly", "is_active": 1},
    {"source_name": "dividends", "amount_per_period": 25000, "frequency": "monthly", "is_active": 1}
  ],
  "expenses": [
    {"category": "housing", "amount": 25000, "frequency": "monthly", "is_recurring": 1},
    {"category": "other", "amount": 40000, "frequency": "monthly", "is_recurring": 1}
  ],
  "assets": [
    {"asset_type": "property", "description": "primary + vacation", "estimated_value": 9500000},
    {"asset_type": "cash", "description": "treasury+cash", "estimated_value": 3000000}
  ],
  "debts": [{"debt_type": "mortgage", "description": "primary", "balance": 2200000,
             "interest_rate": 0.045, "min_payment": 11000}],
  "portfolio_holdings": [
    {"ticker": "VTI", "asset_class": "etf", "shares": 8000, "cost_basis": 2200000, "last_known_price": 360, "last_updated": "2026-05-01"},
    {"ticker": "VXUS", "asset_class": "etf", "shares": 12000, "cost_basis": 1100000, "last_known_price": 95, "last_updated": "2026-05-01"},
    {"ticker": "BND", "asset_class": "bond", "shares": 30000, "cost_basis": 2150000, "last_known_price": 72, "last_updated": "2026-05-01"}
  ],
  "transactions": [],
  "goals": [
    {"goal_name": "estate_transfer", "target_amount": 25000000, "current_amount": 15500000, "priority": 1}
  ],
  "investment_allocation_targets": [
    {"vehicle": "index_funds", "target_pct": 0.6, "expected_annual_return": 0.10, "is_tax_advantaged": 0},
    {"vehicle": "bonds", "target_pct": 0.2, "expected_annual_return": 0.04, "is_tax_advantaged": 0},
    {"vehicle": "reit", "target_pct": 0.1, "expected_annual_return": 0.08, "is_tax_advantaged": 0},
    {"vehicle": "other", "target_pct": 0.1, "expected_annual_return": 0.07, "is_tax_advantaged": 0}
  ]
}
